{"config":{"output_file":null,"full_docs":false,"pub_only":true,"reachable_only":true,"distro_crate":false,"signatures":false,"borrow_data":false},"version":"0.19.0","compilation":{"directory":"C:\\Users\\kelvin\\.cargo\\registry\\src\\github.com-1ecc6299db9ec823\\iovec-0.1.2","program":"C:\\Users\\kelvin\\.rustup\\toolchains\\nightly-x86_64-pc-windows-gnu\\bin\\rls.exe","arguments":["--crate-name","iovec","C:\\Users\\kelvin\\.cargo\\registry\\src\\github.com-1ecc6299db9ec823\\iovec-0.1.2\\src\\lib.rs","--color","never","--crate-type","lib","--emit=dep-info,metadata","-C","debuginfo=2","-C","metadata=14de09f4befc3db6","-C","extra-filename=-14de09f4befc3db6","--out-dir","c:\\workspace\\rust\\rust_example\\tokio\\target\\rls\\debug\\deps","-L","dependency=c:\\workspace\\rust\\rust_example\\tokio\\target\\rls\\debug\\deps","--extern","winapi=c:\\workspace\\rust\\rust_example\\tokio\\target\\rls\\debug\\deps\\libwinapi-a6d5a59f8def4aa4.rmeta","--cap-lints","allow","--error-format=json","--sysroot","C:\\Users\\kelvin\\.rustup/toolchains/nightly-x86_64-pc-windows-gnu"],"output":"c:\\workspace\\rust\\rust_example\\tokio\\target\\rls\\debug\\deps\\libiovec-14de09f4befc3db6.rmeta"},"prelude":{"crate_id":{"name":"iovec","disambiguator":[16757187235483250868,2650587258674849339]},"crate_root":"C:\\Users\\kelvin\\.cargo\\registry\\src\\github.com-1ecc6299db9ec823\\iovec-0.1.2\\src","external_crates":[{"file_name":"C:\\Users\\kelvin\\.cargo\\registry\\src\\github.com-1ecc6299db9ec823\\iovec-0.1.2\\src\\lib.rs","num":1,"id":{"name":"std","disambiguator":[13465627154104885588,6991075649319289830]}},{"file_name":"C:\\Users\\kelvin\\.cargo\\registry\\src\\github.com-1ecc6299db9ec823\\iovec-0.1.2\\src\\lib.rs","num":2,"id":{"name":"core","disambiguator":[15938113673253397451,5083388889884411469]}},{"file_name":"C:\\Users\\kelvin\\.cargo\\registry\\src\\github.com-1ecc6299db9ec823\\iovec-0.1.2\\src\\lib.rs","num":3,"id":{"name":"compiler_builtins","disambiguator":[739839320542720038,9409543303601686690]}},{"file_name":"C:\\Users\\kelvin\\.cargo\\registry\\src\\github.com-1ecc6299db9ec823\\iovec-0.1.2\\src\\lib.rs","num":4,"id":{"name":"rustc_std_workspace_core","disambiguator":[597854396232386165,6457262730519913926]}},{"file_name":"C:\\Users\\kelvin\\.cargo\\registry\\src\\github.com-1ecc6299db9ec823\\iovec-0.1.2\\src\\lib.rs","num":5,"id":{"name":"alloc","disambiguator":[11209801991847627747,11262992578870664411]}},{"file_name":"C:\\Users\\kelvin\\.cargo\\registry\\src\\github.com-1ecc6299db9ec823\\iovec-0.1.2\\src\\lib.rs","num":6,"id":{"name":"libc","disambiguator":[11320595250720628662,12065876561410777570]}},{"file_name":"C:\\Users\\kelvin\\.cargo\\registry\\src\\github.com-1ecc6299db9ec823\\iovec-0.1.2\\src\\lib.rs","num":7,"id":{"name":"unwind","disambiguator":[6314965320923323477,3024863150126497615]}},{"file_name":"C:\\Users\\kelvin\\.cargo\\registry\\src\\github.com-1ecc6299db9ec823\\iovec-0.1.2\\src\\lib.rs","num":8,"id":{"name":"cfg_if","disambiguator":[596055500221654183,9739346022537222307]}},{"file_name":"C:\\Users\\kelvin\\.cargo\\registry\\src\\github.com-1ecc6299db9ec823\\iovec-0.1.2\\src\\lib.rs","num":9,"id":{"name":"hashbrown","disambiguator":[14810875666771245997,13744882673731881574]}},{"file_name":"C:\\Users\\kelvin\\.cargo\\registry\\src\\github.com-1ecc6299db9ec823\\iovec-0.1.2\\src\\lib.rs","num":10,"id":{"name":"rustc_std_workspace_alloc","disambiguator":[12822529103219551998,14746601954566823581]}},{"file_name":"C:\\Users\\kelvin\\.cargo\\registry\\src\\github.com-1ecc6299db9ec823\\iovec-0.1.2\\src\\lib.rs","num":11,"id":{"name":"backtrace","disambiguator":[313502329962680739,13994979928151604268]}},{"file_name":"C:\\Users\\kelvin\\.cargo\\registry\\src\\github.com-1ecc6299db9ec823\\iovec-0.1.2\\src\\lib.rs","num":12,"id":{"name":"rustc_demangle","disambiguator":[7952646223812396090,7303923247171922059]}},{"file_name":"C:\\Users\\kelvin\\.cargo\\registry\\src\\github.com-1ecc6299db9ec823\\iovec-0.1.2\\src\\lib.rs","num":13,"id":{"name":"backtrace_sys","disambiguator":[16203046759340916593,3575221768724706906]}},{"file_name":"C:\\Users\\kelvin\\.cargo\\registry\\src\\github.com-1ecc6299db9ec823\\iovec-0.1.2\\src\\lib.rs","num":14,"id":{"name":"panic_unwind","disambiguator":[7732548582733950903,8353437360250403284]}},{"file_name":"C:\\Users\\kelvin\\.cargo\\registry\\src\\github.com-1ecc6299db9ec823\\iovec-0.1.2\\src\\lib.rs","num":15,"id":{"name":"winapi","disambiguator":[13946310276844343479,6006214718415248670]}}],"span":{"file_name":"C:\\Users\\kelvin\\.cargo\\registry\\src\\github.com-1ecc6299db9ec823\\iovec-0.1.2\\src\\lib.rs","byte_start":0,"byte_end":4347,"line_start":1,"line_end":164,"column_start":1,"column_end":2}},"imports":[],"defs":[{"kind":"Mod","id":{"krate":0,"index":0},"span":{"file_name":"C:\\Users\\kelvin\\.cargo\\registry\\src\\github.com-1ecc6299db9ec823\\iovec-0.1.2\\src\\lib.rs","byte_start":0,"byte_end":4347,"line_start":1,"line_end":164,"column_start":1,"column_end":2},"name":"","qualname":"::","value":"C:\\Users\\kelvin\\.cargo\\registry\\src\\github.com-1ecc6299db9ec823\\iovec-0.1.2\\src\\lib.rs","parent":null,"children":[{"krate":0,"index":10},{"krate":0,"index":11},{"krate":0,"index":12},{"krate":0,"index":13},{"krate":0,"index":38},{"krate":0,"index":41},{"krate":0,"index":42},{"krate":0,"index":44},{"krate":0,"index":49},{"krate":0,"index":52},{"krate":0,"index":54},{"krate":0,"index":57},{"krate":0,"index":60},{"krate":0,"index":63}],"decl_id":null,"docs":" A specialized byte slice type for performing vectored I/O operations.","sig":null,"attributes":[]},{"kind":"Struct","id":{"krate":0,"index":22},"span":{"file_name":"C:\\Users\\kelvin\\.cargo\\registry\\src\\github.com-1ecc6299db9ec823\\iovec-0.1.2\\src\\sys\\windows.rs","byte_start":4744,"byte_end":4749,"line_start":4,"line_end":4,"column_start":12,"column_end":17},"name":"IoVec","qualname":"::sys::windows::IoVec","value":"IoVec {  }","parent":null,"children":[{"krate":0,"index":23}],"decl_id":null,"docs":"","sig":null,"attributes":[]},{"kind":"Method","id":{"krate":0,"index":26},"span":{"file_name":"C:\\Users\\kelvin\\.cargo\\registry\\src\\github.com-1ecc6299db9ec823\\iovec-0.1.2\\src\\sys\\windows.rs","byte_start":4846,"byte_end":4852,"line_start":11,"line_end":11,"column_start":12,"column_end":18},"name":"as_ref","qualname":"<IoVec>::as_ref","value":"fn (&self) -> &[u8]","parent":null,"children":[],"decl_id":null,"docs":"","sig":null,"attributes":[]},{"kind":"Method","id":{"krate":0,"index":27},"span":{"file_name":"C:\\Users\\kelvin\\.cargo\\registry\\src\\github.com-1ecc6299db9ec823\\iovec-0.1.2\\src\\sys\\windows.rs","byte_start":5027,"byte_end":5033,"line_start":18,"line_end":18,"column_start":12,"column_end":18},"name":"as_mut","qualname":"<IoVec>::as_mut","value":"fn (&mut self) -> &mut [u8]","parent":null,"children":[],"decl_id":null,"docs":"","sig":null,"attributes":[]},{"kind":"Const","id":{"krate":0,"index":41},"span":{"file_name":"C:\\Users\\kelvin\\.cargo\\registry\\src\\github.com-1ecc6299db9ec823\\iovec-0.1.2\\src\\lib.rs","byte_start":425,"byte_end":435,"line_start":23,"line_end":23,"column_start":11,"column_end":21},"name":"MAX_LENGTH","qualname":"::MAX_LENGTH","value":"usize","parent":null,"children":[],"decl_id":null,"docs":" Max length of an `IoVec` slice.","sig":null,"attributes":[]},{"kind":"Struct","id":{"krate":0,"index":42},"span":{"file_name":"C:\\Users\\kelvin\\.cargo\\registry\\src\\github.com-1ecc6299db9ec823\\iovec-0.1.2\\src\\lib.rs","byte_start":1433,"byte_end":1438,"line_start":56,"line_end":56,"column_start":12,"column_end":17},"name":"IoVec","qualname":"::IoVec","value":"IoVec {  }","parent":null,"children":[{"krate":0,"index":43}],"decl_id":null,"docs":" A specialized byte slice type for performing vectored I/O operations.","sig":null,"attributes":[]},{"kind":"Method","id":{"krate":0,"index":45},"span":{"file_name":"C:\\Users\\kelvin\\.cargo\\registry\\src\\github.com-1ecc6299db9ec823\\iovec-0.1.2\\src\\lib.rs","byte_start":1489,"byte_end":1499,"line_start":61,"line_end":61,"column_start":12,"column_end":22},"name":"from_bytes","qualname":"<IoVec>::from_bytes","value":"fn (slice: &[u8]) -> Option<&IoVec>","parent":null,"children":[],"decl_id":null,"docs":"","sig":null,"attributes":[]},{"kind":"Method","id":{"krate":0,"index":46},"span":{"file_name":"C:\\Users\\kelvin\\.cargo\\registry\\src\\github.com-1ecc6299db9ec823\\iovec-0.1.2\\src\\lib.rs","byte_start":1734,"byte_end":1748,"line_start":71,"line_end":71,"column_start":12,"column_end":26},"name":"from_bytes_mut","qualname":"<IoVec>::from_bytes_mut","value":"fn (slice: &mut [u8]) -> Option<&mut IoVec>","parent":null,"children":[],"decl_id":null,"docs":"","sig":null,"attributes":[]},{"kind":"Method","id":{"krate":0,"index":47},"span":{"file_name":"C:\\Users\\kelvin\\.cargo\\registry\\src\\github.com-1ecc6299db9ec823\\iovec-0.1.2\\src\\lib.rs","byte_start":2073,"byte_end":2081,"line_start":83,"line_end":83,"column_start":12,"column_end":20},"name":"as_bytes","qualname":"<IoVec>::as_bytes","value":"fn (&self) -> &[u8]","parent":null,"children":[],"decl_id":null,"docs":"","sig":null,"attributes":[{"value":"deprecated(since = \"0.1.0\", note = \"deref instead\")","span":{"file_name":"C:\\Users\\kelvin\\.cargo\\registry\\src\\github.com-1ecc6299db9ec823\\iovec-0.1.2\\src\\lib.rs","byte_start":1988,"byte_end":2042,"line_start":81,"line_end":81,"column_start":5,"column_end":59}}]},{"kind":"Method","id":{"krate":0,"index":48},"span":{"file_name":"C:\\Users\\kelvin\\.cargo\\registry\\src\\github.com-1ecc6299db9ec823\\iovec-0.1.2\\src\\lib.rs","byte_start":2212,"byte_end":2224,"line_start":89,"line_end":89,"column_start":12,"column_end":24},"name":"as_mut_bytes","qualname":"<IoVec>::as_mut_bytes","value":"fn (&mut self) -> &mut [u8]","parent":null,"children":[],"decl_id":null,"docs":"","sig":null,"attributes":[{"value":"deprecated(since = \"0.1.0\", note = \"deref instead\")","span":{"file_name":"C:\\Users\\kelvin\\.cargo\\registry\\src\\github.com-1ecc6299db9ec823\\iovec-0.1.2\\src\\lib.rs","byte_start":2127,"byte_end":2181,"line_start":87,"line_end":87,"column_start":5,"column_end":59}}]}],"impls":[{"id":0,"kind":"Inherent","span":{"file_name":"C:\\Users\\kelvin\\.cargo\\registry\\src\\github.com-1ecc6299db9ec823\\iovec-0.1.2\\src\\sys\\windows.rs","byte_start":4827,"byte_end":4832,"line_start":10,"line_end":10,"column_start":6,"column_end":11},"value":"","parent":null,"children":[{"krate":0,"index":26},{"krate":0,"index":27},{"krate":0,"index":28}],"docs":"","sig":null,"attributes":[]},{"id":1,"kind":"Inherent","span":{"file_name":"C:\\Users\\kelvin\\.cargo\\registry\\src\\github.com-1ecc6299db9ec823\\iovec-0.1.2\\src\\lib.rs","byte_start":1470,"byte_end":1475,"line_start":60,"line_end":60,"column_start":6,"column_end":11},"value":"","parent":null,"children":[{"krate":0,"index":45},{"krate":0,"index":46},{"krate":0,"index":47},{"krate":0,"index":48}],"docs":"","sig":null,"attributes":[]},{"id":2,"kind":"Direct","span":{"file_name":"C:\\Users\\kelvin\\.cargo\\registry\\src\\github.com-1ecc6299db9ec823\\iovec-0.1.2\\src\\lib.rs","byte_start":2300,"byte_end":2305,"line_start":94,"line_end":94,"column_start":21,"column_end":26},"value":"","parent":null,"children":[{"krate":0,"index":50},{"krate":0,"index":51}],"docs":"","sig":null,"attributes":[]},{"id":3,"kind":"Direct","span":{"file_name":"C:\\Users\\kelvin\\.cargo\\registry\\src\\github.com-1ecc6299db9ec823\\iovec-0.1.2\\src\\lib.rs","byte_start":2423,"byte_end":2428,"line_start":102,"line_end":102,"column_start":24,"column_end":29},"value":"","parent":null,"children":[{"krate":0,"index":53}],"docs":"","sig":null,"attributes":[]}],"refs":[],"macro_refs":[],"relations":[{"span":{"file_name":"C:\\Users\\kelvin\\.cargo\\registry\\src\\github.com-1ecc6299db9ec823\\iovec-0.1.2\\src\\sys\\windows.rs","byte_start":4827,"byte_end":4832,"line_start":10,"line_end":10,"column_start":6,"column_end":11},"kind":{"Impl":{"id":0}},"from":{"krate":0,"index":22},"to":{"krate":4294967295,"index":4294967295}},{"span":{"file_name":"C:\\Users\\kelvin\\.cargo\\registry\\src\\github.com-1ecc6299db9ec823\\iovec-0.1.2\\src\\lib.rs","byte_start":1470,"byte_end":1475,"line_start":60,"line_end":60,"column_start":6,"column_end":11},"kind":{"Impl":{"id":1}},"from":{"krate":0,"index":42},"to":{"krate":4294967295,"index":4294967295}},{"span":{"file_name":"C:\\Users\\kelvin\\.cargo\\registry\\src\\github.com-1ecc6299db9ec823\\iovec-0.1.2\\src\\lib.rs","byte_start":2300,"byte_end":2305,"line_start":94,"line_end":94,"column_start":21,"column_end":26},"kind":{"Impl":{"id":2}},"from":{"krate":0,"index":42},"to":{"krate":2,"index":1601}},{"span":{"file_name":"C:\\Users\\kelvin\\.cargo\\registry\\src\\github.com-1ecc6299db9ec823\\iovec-0.1.2\\src\\lib.rs","byte_start":2423,"byte_end":2428,"line_start":102,"line_end":102,"column_start":24,"column_end":29},"kind":{"Impl":{"id":3}},"from":{"krate":0,"index":42},"to":{"krate":2,"index":1612}}]}